graphslam/__init__.py
graphslam/graph.py
graphslam/load.py
graphslam/util.py
graphslam/vertex.py
graphslam/edge/__init__.py
graphslam/edge/base_edge.py
graphslam/edge/edge_odometry.py
graphslam/pose/__init__.py
graphslam/pose/base_pose.py
graphslam/pose/r2.py
graphslam/pose/r3.py
graphslam/pose/se2.py
graphslam/pose/se3.py
graphslam-0.0.8.dist-info/LICENSE
graphslam-0.0.8.dist-info/METADATA
graphslam-0.0.8.dist-info/WHEEL
graphslam-0.0.8.dist-info/top_level.txt
graphslam-0.0.8.dist-info/RECORD
