Metadata-Version: 2.1
Name: graphslam
Version: 0.0.8
Summary: Graph SLAM solver in Python
Home-page: https://github.com/JeffLIrion/python-graphslam
Author: Jeff Irion
Author-email: jefflirion@users.noreply.github.com
License: MIT
Keywords: graphslam,slam,graph,optimization,mapping
Platform: UNKNOWN
Classifier: License :: OSI Approved :: MIT License
Classifier: Operating System :: OS Independent
Classifier: Programming Language :: Python :: 3
License-File: LICENSE
Requires-Dist: numpy
Requires-Dist: scipy
